py_spring_core-0.0.17.dist-info/METADATA
py_spring_core-0.0.17.dist-info/WHEEL
py_spring_core-0.0.17.dist-info/entry_points.txt
py_spring_core-0.0.17.dist-info/licenses/LICENSE
py_spring_core/__init__.py
py_spring_core/commons/class_scanner.py
py_spring_core/commons/config_file_template_generator/config_file_template_generator.py
py_spring_core/commons/config_file_template_generator/templates.py
py_spring_core/commons/file_path_scanner.py
py_spring_core/commons/json_config_repository.py
py_spring_core/commons/type_checking_service.py
py_spring_core/core/application/application_config.py
py_spring_core/core/application/commons.py
py_spring_core/core/application/context/application_context.py
py_spring_core/core/application/context/application_context_config.py
py_spring_core/core/application/loguru_config.py
py_spring_core/core/application/py_spring_application.py
py_spring_core/core/entities/bean_collection.py
py_spring_core/core/entities/component.py
py_spring_core/core/entities/controllers/__init__.py
py_spring_core/core/entities/controllers/rest_controller.py
py_spring_core/core/entities/controllers/route_mapping.py
py_spring_core/core/entities/entity_provider.py
py_spring_core/core/entities/properties/properties.py
py_spring_core/core/entities/properties/properties_loader.py
py_spring_core/core/interfaces/application_context_required.py
py_spring_core/core/utils.py
py_spring_core/event/application_event_handler_registry.py
py_spring_core/event/application_event_publisher.py
py_spring_core/event/commons.py
py_spring_core-0.0.17.dist-info/RECORD
