Metadata-Version: 2.1
Name: py_spring_core
Version: 0.0.17
Summary: PySpring is a Python web framework inspired by Spring Boot, combining FastAPI, and Pydantic for building scalable web applications with auto dependency injection, configuration management, and a web server.
Author-Email: William Chen <OW6201231@gmail.com>
License: MIT
Requires-Python: <3.13,>=3.10
Requires-Dist: annotated-types>=0.7.0
Requires-Dist: anyio>=4.4.0
Requires-Dist: certifi>=2023.7.22
Requires-Dist: click>=8.1.7
Requires-Dist: dnspython>=2.6.1
Requires-Dist: email-validator>=2.2.0
Requires-Dist: exceptiongroup>=1.2.2
Requires-Dist: fastapi>=0.115.12
Requires-Dist: fastapi-cli>=0.0.5
Requires-Dist: greenlet>=3.0.3
Requires-Dist: h11>=0.16.0
Requires-Dist: httpcore>=1.0.9
Requires-Dist: httptools>=0.6.1
Requires-Dist: httpx>=0.27.0
Requires-Dist: idna>=3.7
Requires-Dist: itsdangerous>=2.2.0
Requires-Dist: Jinja2>=3.1.6
Requires-Dist: loguru>=0.7.2
Requires-Dist: markdown-it-py>=3.0.0
Requires-Dist: MarkupSafe>=2.1.5
Requires-Dist: mdurl>=0.1.2
Requires-Dist: orjson>=3.10.7
Requires-Dist: Pygments>=2.18.0
Requires-Dist: python-dotenv>=1.0.1
Requires-Dist: python-multipart>=0.0.18
Requires-Dist: PyYAML>=6.0.2
Requires-Dist: rich>=13.7.1
Requires-Dist: shellingham>=1.5.4
Requires-Dist: sniffio>=1.3.1
Requires-Dist: starlette<0.47.0,>=0.40.0
Requires-Dist: typer>=0.12.5
Requires-Dist: typing-extensions>=4.12.2
Requires-Dist: ujson>=5.10.0
Requires-Dist: uvicorn>=0.30.5
Requires-Dist: uvloop>=0.19.0
Requires-Dist: watchfiles>=0.23.0
Requires-Dist: websockets>=12.0
Requires-Dist: cachetools>=5.5.0
Requires-Dist: pydantic>=2.11.7
